<?xml version='1.0' encoding='utf-8'?>
<graphml xmlns="http://graphml.graphdrawing.org/xmlns" xmlns:xsi="http://www.w3.org/2001/XMLSchema-instance" xsi:schemaLocation="http://graphml.graphdrawing.org/xmlns http://graphml.graphdrawing.org/xmlns/1.0/graphml.xsd">
  <graph edgedefault="undirected">
    <node id="93489_at" />
    <node id="99083_at" />
    <node id="103962_at" />
    <node id="92695_at" />
    <node id="98408_at" />
    <node id="96177_at" />
    <node id="102416_at" />
    <node id="97714_r_at" />
    <node id="93581_at" />
    <node id="94057_g_at" />
    <node id="99541_at" />
    <node id="94499_at" />
    <node id="93585_at" />
    <node id="102796_at" />
    <node id="95446_at" />
    <node id="103882_at" />
    <node id="102162_at" />
    <node id="94203_at" />
    <node id="93228_at" />
    <node id="97146_g_at" />
    <node id="96334_f_at" />
    <node id="99674_at" />
    <node id="96276_r_at" />
    <node id="104120_at" />
    <node id="100554_at" />
    <node id="96598_at" />
    <node id="96768_at" />
    <node id="98036_at" />
    <node id="104135_at" />
    <node id="97786_at" />
    <node id="104610_at" />
    <node id="99843_at" />
    <node id="103699_i_at" />
    <node id="103614_at" />
    <node id="103594_at" />
    <node id="99179_at" />
    <node id="95758_at" />
    <node id="102084_f_at" />
    <node id="104560_at" />
    <node id="103643_at" />
    <node id="97742_s_at" />
    <node id="103469_at" />
    <node id="96829_at" />
    <node id="94335_r_at" />
    <node id="103706_at" />
    <node id="101667_at" />
    <node id="95043_at" />
    <node id="100772_g_at" />
    <node id="99809_at" />
    <node id="97819_at" />
    <node id="95327_at" />
    <node id="95283_at" />
    <node id="96224_at" />
    <node id="95738_at" />
    <node id="96047_at" />
    <node id="102003_at" />
    <node id="99070_at" />
    <node id="95735_at" />
    <node id="98295_at" />
    <node id="96866_at" />
    <node id="94380_at" />
    <node id="101334_at" />
    <node id="103439_at" />
    <node id="96130_at" />
    <node id="93901_at" />
    <node id="98320_at" />
    <edge source="93489_at" target="100554_at" />
    <edge source="93489_at" target="103643_at" />
    <edge source="93489_at" target="94499_at" />
    <edge source="93489_at" target="103962_at" />
    <edge source="93489_at" target="103614_at" />
    <edge source="93489_at" target="103469_at" />
    <edge source="93489_at" target="100772_g_at" />
    <edge source="93489_at" target="99541_at" />
    <edge source="93489_at" target="97714_r_at" />
    <edge source="93489_at" target="96130_at" />
    <edge source="93489_at" target="99809_at" />
    <edge source="93489_at" target="98408_at" />
    <edge source="93489_at" target="102796_at" />
    <edge source="93489_at" target="95446_at" />
    <edge source="93489_at" target="97819_at" />
    <edge source="93489_at" target="94203_at" />
    <edge source="93489_at" target="101667_at" />
    <edge source="93489_at" target="96224_at" />
    <edge source="93489_at" target="95738_at" />
    <edge source="93489_at" target="96047_at" />
    <edge source="93489_at" target="95327_at" />
    <edge source="93489_at" target="96598_at" />
    <edge source="93489_at" target="92695_at" />
    <edge source="93489_at" target="98036_at" />
    <edge source="93489_at" target="104135_at" />
    <edge source="93489_at" target="97786_at" />
    <edge source="93489_at" target="104610_at" />
    <edge source="93489_at" target="99843_at" />
    <edge source="93489_at" target="94380_at" />
    <edge source="93489_at" target="99179_at" />
    <edge source="93489_at" target="104120_at" />
    <edge source="93489_at" target="96177_at" />
    <edge source="93489_at" target="99070_at" />
    <edge source="93489_at" target="101334_at" />
    <edge source="99083_at" target="95283_at" />
    <edge source="99083_at" target="96334_f_at" />
    <edge source="99083_at" target="104560_at" />
    <edge source="99083_at" target="95738_at" />
    <edge source="99083_at" target="97786_at" />
    <edge source="99083_at" target="103469_at" />
    <edge source="99083_at" target="99070_at" />
    <edge source="99083_at" target="96177_at" />
    <edge source="99083_at" target="95758_at" />
    <edge source="99083_at" target="103882_at" />
    <edge source="99083_at" target="100554_at" />
    <edge source="99083_at" target="93581_at" />
    <edge source="99083_at" target="99541_at" />
    <edge source="99083_at" target="94499_at" />
    <edge source="99083_at" target="94380_at" />
    <edge source="99083_at" target="93585_at" />
    <edge source="99083_at" target="102084_f_at" />
    <edge source="99083_at" target="97819_at" />
    <edge source="99083_at" target="94057_g_at" />
    <edge source="103962_at" target="96177_at" />
    <edge source="103962_at" target="103469_at" />
    <edge source="103962_at" target="97714_r_at" />
    <edge source="103962_at" target="99541_at" />
    <edge source="103962_at" target="102796_at" />
    <edge source="103962_at" target="94499_at" />
    <edge source="103962_at" target="93585_at" />
    <edge source="103962_at" target="103882_at" />
    <edge source="103962_at" target="93228_at" />
    <edge source="103962_at" target="96334_f_at" />
    <edge source="103962_at" target="98408_at" />
    <edge source="103962_at" target="95738_at" />
    <edge source="103962_at" target="104120_at" />
    <edge source="103962_at" target="97819_at" />
    <edge source="103962_at" target="99070_at" />
    <edge source="103962_at" target="100554_at" />
    <edge source="103962_at" target="97786_at" />
    <edge source="103962_at" target="104610_at" />
    <edge source="103962_at" target="94380_at" />
    <edge source="103962_at" target="102084_f_at" />
    <edge source="103962_at" target="96130_at" />
    <edge source="103962_at" target="101334_at" />
    <edge source="92695_at" target="96130_at" />
    <edge source="92695_at" target="96177_at" />
    <edge source="92695_at" target="97714_r_at" />
    <edge source="92695_at" target="99541_at" />
    <edge source="92695_at" target="102796_at" />
    <edge source="92695_at" target="94499_at" />
    <edge source="92695_at" target="97819_at" />
    <edge source="92695_at" target="93228_at" />
    <edge source="92695_at" target="98408_at" />
    <edge source="92695_at" target="95738_at" />
    <edge source="92695_at" target="96047_at" />
    <edge source="92695_at" target="100554_at" />
    <edge source="92695_at" target="95283_at" />
    <edge source="92695_at" target="95735_at" />
    <edge source="92695_at" target="97786_at" />
    <edge source="92695_at" target="104610_at" />
    <edge source="92695_at" target="103699_i_at" />
    <edge source="92695_at" target="94380_at" />
    <edge source="92695_at" target="104120_at" />
    <edge source="92695_at" target="99070_at" />
    <edge source="92695_at" target="101334_at" />
    <edge source="98408_at" target="96177_at" />
    <edge source="98408_at" target="94203_at" />
    <edge source="98408_at" target="97742_s_at" />
    <edge source="98408_at" target="94380_at" />
    <edge source="98408_at" target="94335_r_at" />
    <edge source="98408_at" target="100772_g_at" />
    <edge source="98408_at" target="99541_at" />
    <edge source="98408_at" target="97714_r_at" />
    <edge source="98408_at" target="94499_at" />
    <edge source="98408_at" target="99809_at" />
    <edge source="98408_at" target="97819_at" />
    <edge source="98408_at" target="93228_at" />
    <edge source="98408_at" target="96224_at" />
    <edge source="98408_at" target="95738_at" />
    <edge source="98408_at" target="97786_at" />
    <edge source="98408_at" target="100554_at" />
    <edge source="98408_at" target="99070_at" />
    <edge source="98408_at" target="96768_at" />
    <edge source="98408_at" target="98036_at" />
    <edge source="98408_at" target="104135_at" />
    <edge source="98408_at" target="104610_at" />
    <edge source="98408_at" target="99843_at" />
    <edge source="98408_at" target="103699_i_at" />
    <edge source="98408_at" target="103614_at" />
    <edge source="98408_at" target="99179_at" />
    <edge source="98408_at" target="101334_at" />
    <edge source="98408_at" target="95327_at" />
    <edge source="98408_at" target="96130_at" />
    <edge source="98408_at" target="98320_at" />
    <edge source="96177_at" target="100554_at" />
    <edge source="96177_at" target="94203_at" />
    <edge source="96177_at" target="95283_at" />
    <edge source="96177_at" target="103614_at" />
    <edge source="96177_at" target="102416_at" />
    <edge source="96177_at" target="100772_g_at" />
    <edge source="96177_at" target="93581_at" />
    <edge source="96177_at" target="103706_at" />
    <edge source="96177_at" target="99541_at" />
    <edge source="96177_at" target="97714_r_at" />
    <edge source="96177_at" target="94499_at" />
    <edge source="96177_at" target="99809_at" />
    <edge source="96177_at" target="95446_at" />
    <edge source="96177_at" target="97819_at" />
    <edge source="96177_at" target="95327_at" />
    <edge source="96177_at" target="93228_at" />
    <edge source="96177_at" target="104135_at" />
    <edge source="96177_at" target="96224_at" />
    <edge source="96177_at" target="95738_at" />
    <edge source="96177_at" target="103439_at" />
    <edge source="96177_at" target="99070_at" />
    <edge source="96177_at" target="102003_at" />
    <edge source="96177_at" target="98036_at" />
    <edge source="96177_at" target="97146_g_at" />
    <edge source="96177_at" target="97786_at" />
    <edge source="96177_at" target="104610_at" />
    <edge source="96177_at" target="99843_at" />
    <edge source="96177_at" target="94380_at" />
    <edge source="96177_at" target="99179_at" />
    <edge source="96177_at" target="104560_at" />
    <edge source="96177_at" target="96130_at" />
    <edge source="96177_at" target="101334_at" />
    <edge source="102416_at" target="95283_at" />
    <edge source="102416_at" target="96334_f_at" />
    <edge source="102416_at" target="104560_at" />
    <edge source="102416_at" target="95738_at" />
    <edge source="102416_at" target="97786_at" />
    <edge source="102416_at" target="103469_at" />
    <edge source="102416_at" target="99070_at" />
    <edge source="102416_at" target="95758_at" />
    <edge source="102416_at" target="103882_at" />
    <edge source="102416_at" target="100554_at" />
    <edge source="102416_at" target="93581_at" />
    <edge source="102416_at" target="99541_at" />
    <edge source="102416_at" target="94499_at" />
    <edge source="102416_at" target="94380_at" />
    <edge source="102416_at" target="93585_at" />
    <edge source="102416_at" target="102084_f_at" />
    <edge source="102416_at" target="97819_at" />
    <edge source="102416_at" target="94057_g_at" />
    <edge source="97714_r_at" target="95283_at" />
    <edge source="97714_r_at" target="96768_at" />
    <edge source="97714_r_at" target="100772_g_at" />
    <edge source="97714_r_at" target="99541_at" />
    <edge source="97714_r_at" target="94499_at" />
    <edge source="97714_r_at" target="96224_at" />
    <edge source="97714_r_at" target="102162_at" />
    <edge source="97714_r_at" target="97819_at" />
    <edge source="97714_r_at" target="103614_at" />
    <edge source="97714_r_at" target="93228_at" />
    <edge source="97714_r_at" target="104135_at" />
    <edge source="97714_r_at" target="95738_at" />
    <edge source="97714_r_at" target="97786_at" />
    <edge source="97714_r_at" target="95327_at" />
    <edge source="97714_r_at" target="99070_at" />
    <edge source="97714_r_at" target="98036_at" />
    <edge source="97714_r_at" target="97146_g_at" />
    <edge source="97714_r_at" target="100554_at" />
    <edge source="97714_r_at" target="104610_at" />
    <edge source="97714_r_at" target="94380_at" />
    <edge source="97714_r_at" target="99179_at" />
    <edge source="97714_r_at" target="104560_at" />
    <edge source="97714_r_at" target="96130_at" />
    <edge source="93581_at" target="103643_at" />
    <edge source="93581_at" target="95283_at" />
    <edge source="93581_at" target="96829_at" />
    <edge source="93581_at" target="103469_at" />
    <edge source="93581_at" target="96334_f_at" />
    <edge source="93581_at" target="100772_g_at" />
    <edge source="93581_at" target="103706_at" />
    <edge source="93581_at" target="101667_at" />
    <edge source="93581_at" target="95043_at" />
    <edge source="93581_at" target="94499_at" />
    <edge source="93581_at" target="99179_at" />
    <edge source="93581_at" target="93585_at" />
    <edge source="93581_at" target="99809_at" />
    <edge source="93581_at" target="95446_at" />
    <edge source="93581_at" target="97819_at" />
    <edge source="93581_at" target="95738_at" />
    <edge source="93581_at" target="104135_at" />
    <edge source="93581_at" target="104120_at" />
    <edge source="93581_at" target="99674_at" />
    <edge source="93581_at" target="96276_r_at" />
    <edge source="93581_at" target="96047_at" />
    <edge source="93581_at" target="103439_at" />
    <edge source="93581_at" target="96598_at" />
    <edge source="93581_at" target="102003_at" />
    <edge source="93581_at" target="98036_at" />
    <edge source="93581_at" target="97146_g_at" />
    <edge source="93581_at" target="98295_at" />
    <edge source="93581_at" target="96866_at" />
    <edge source="93581_at" target="103699_i_at" />
    <edge source="93581_at" target="94380_at" />
    <edge source="93581_at" target="99541_at" />
    <edge source="93581_at" target="95758_at" />
    <edge source="93581_at" target="102084_f_at" />
    <edge source="93581_at" target="104560_at" />
    <edge source="93581_at" target="94057_g_at" />
    <edge source="93581_at" target="98320_at" />
    <edge source="94057_g_at" target="103643_at" />
    <edge source="94057_g_at" target="95758_at" />
    <edge source="94057_g_at" target="103706_at" />
    <edge source="94057_g_at" target="95043_at" />
    <edge source="94057_g_at" target="93585_at" />
    <edge source="94057_g_at" target="99809_at" />
    <edge source="94057_g_at" target="103469_at" />
    <edge source="94057_g_at" target="97819_at" />
    <edge source="94057_g_at" target="96334_f_at" />
    <edge source="94057_g_at" target="96276_r_at" />
    <edge source="94057_g_at" target="95738_at" />
    <edge source="94057_g_at" target="103439_at" />
    <edge source="94057_g_at" target="99070_at" />
    <edge source="94057_g_at" target="98036_at" />
    <edge source="94057_g_at" target="97146_g_at" />
    <edge source="94057_g_at" target="98295_at" />
    <edge source="94057_g_at" target="97786_at" />
    <edge source="94057_g_at" target="96829_at" />
    <edge source="94057_g_at" target="102084_f_at" />
    <edge source="94057_g_at" target="104560_at" />
    <edge source="94057_g_at" target="95283_at" />
    <edge source="94057_g_at" target="98320_at" />
    <edge source="99541_at" target="100554_at" />
    <edge source="99541_at" target="103439_at" />
    <edge source="99541_at" target="95283_at" />
    <edge source="99541_at" target="94380_at" />
    <edge source="99541_at" target="100772_g_at" />
    <edge source="99541_at" target="103706_at" />
    <edge source="99541_at" target="94499_at" />
    <edge source="99541_at" target="96224_at" />
    <edge source="99541_at" target="97819_at" />
    <edge source="99541_at" target="95327_at" />
    <edge source="99541_at" target="93228_at" />
    <edge source="99541_at" target="104135_at" />
    <edge source="99541_at" target="95738_at" />
    <edge source="99541_at" target="104560_at" />
    <edge source="99541_at" target="99070_at" />
    <edge source="99541_at" target="98036_at" />
    <edge source="99541_at" target="97146_g_at" />
    <edge source="99541_at" target="97786_at" />
    <edge source="99541_at" target="104610_at" />
    <edge source="99541_at" target="96866_at" />
    <edge source="99541_at" target="103614_at" />
    <edge source="99541_at" target="99179_at" />
    <edge source="99541_at" target="102003_at" />
    <edge source="99541_at" target="96130_at" />
    <edge source="94499_at" target="94203_at" />
    <edge source="94499_at" target="100772_g_at" />
    <edge source="94499_at" target="102796_at" />
    <edge source="94499_at" target="95446_at" />
    <edge source="94499_at" target="103882_at" />
    <edge source="94499_at" target="93228_at" />
    <edge source="94499_at" target="97146_g_at" />
    <edge source="94499_at" target="104120_at" />
    <edge source="94499_at" target="101667_at" />
    <edge source="94499_at" target="97786_at" />
    <edge source="94499_at" target="100554_at" />
    <edge source="94499_at" target="96598_at" />
    <edge source="94499_at" target="98036_at" />
    <edge source="94499_at" target="104135_at" />
    <edge source="94499_at" target="104610_at" />
    <edge source="94499_at" target="99843_at" />
    <edge source="94499_at" target="103614_at" />
    <edge source="94499_at" target="99179_at" />
    <edge source="94499_at" target="102003_at" />
    <edge source="94499_at" target="103643_at" />
    <edge source="94499_at" target="103469_at" />
    <edge source="94499_at" target="103706_at" />
    <edge source="94499_at" target="99674_at" />
    <edge source="94499_at" target="96224_at" />
    <edge source="94499_at" target="97819_at" />
    <edge source="94499_at" target="99070_at" />
    <edge source="94499_at" target="95738_at" />
    <edge source="94499_at" target="96047_at" />
    <edge source="94499_at" target="103439_at" />
    <edge source="94499_at" target="95283_at" />
    <edge source="94499_at" target="104560_at" />
    <edge source="94499_at" target="94380_at" />
    <edge source="94499_at" target="95327_at" />
    <edge source="94499_at" target="96130_at" />
    <edge source="94499_at" target="101334_at" />
    <edge source="93585_at" target="103643_at" />
    <edge source="93585_at" target="96829_at" />
    <edge source="93585_at" target="103469_at" />
    <edge source="93585_at" target="95043_at" />
    <edge source="93585_at" target="99809_at" />
    <edge source="93585_at" target="97819_at" />
    <edge source="93585_at" target="104135_at" />
    <edge source="93585_at" target="96334_f_at" />
    <edge source="93585_at" target="96276_r_at" />
    <edge source="93585_at" target="95738_at" />
    <edge source="93585_at" target="103882_at" />
    <edge source="93585_at" target="99070_at" />
    <edge source="93585_at" target="100554_at" />
    <edge source="93585_at" target="97146_g_at" />
    <edge source="93585_at" target="98295_at" />
    <edge source="93585_at" target="97786_at" />
    <edge source="93585_at" target="94380_at" />
    <edge source="93585_at" target="95758_at" />
    <edge source="93585_at" target="102084_f_at" />
    <edge source="93585_at" target="98320_at" />
    <edge source="102796_at" target="100554_at" />
    <edge source="102796_at" target="94203_at" />
    <edge source="102796_at" target="95283_at" />
    <edge source="102796_at" target="94335_r_at" />
    <edge source="102796_at" target="100772_g_at" />
    <edge source="102796_at" target="99809_at" />
    <edge source="102796_at" target="95446_at" />
    <edge source="102796_at" target="93228_at" />
    <edge source="102796_at" target="99070_at" />
    <edge source="102796_at" target="99674_at" />
    <edge source="102796_at" target="96224_at" />
    <edge source="102796_at" target="95738_at" />
    <edge source="102796_at" target="96047_at" />
    <edge source="102796_at" target="95327_at" />
    <edge source="102796_at" target="96598_at" />
    <edge source="102796_at" target="95735_at" />
    <edge source="102796_at" target="104135_at" />
    <edge source="102796_at" target="97786_at" />
    <edge source="102796_at" target="104610_at" />
    <edge source="102796_at" target="99843_at" />
    <edge source="102796_at" target="103614_at" />
    <edge source="102796_at" target="99179_at" />
    <edge source="102796_at" target="102003_at" />
    <edge source="102796_at" target="104120_at" />
    <edge source="102796_at" target="101334_at" />
    <edge source="95446_at" target="96334_f_at" />
    <edge source="95446_at" target="104610_at" />
    <edge source="95446_at" target="104120_at" />
    <edge source="95446_at" target="103699_i_at" />
    <edge source="95446_at" target="99070_at" />
    <edge source="95446_at" target="101334_at" />
    <edge source="103882_at" target="93228_at" />
    <edge source="103882_at" target="96334_f_at" />
    <edge source="103882_at" target="103643_at" />
    <edge source="103882_at" target="96047_at" />
    <edge source="103882_at" target="100554_at" />
    <edge source="103882_at" target="104135_at" />
    <edge source="103882_at" target="98295_at" />
    <edge source="103882_at" target="95043_at" />
    <edge source="103882_at" target="94380_at" />
    <edge source="103882_at" target="102084_f_at" />
    <edge source="103882_at" target="97742_s_at" />
    <edge source="103882_at" target="98320_at" />
    <edge source="102162_at" target="104560_at" />
    <edge source="94203_at" target="93228_at" />
    <edge source="94203_at" target="100554_at" />
    <edge source="94203_at" target="104120_at" />
    <edge source="94203_at" target="104610_at" />
    <edge source="94203_at" target="99070_at" />
    <edge source="94203_at" target="101334_at" />
    <edge source="93228_at" target="100554_at" />
    <edge source="93228_at" target="97742_s_at" />
    <edge source="93228_at" target="94380_at" />
    <edge source="93228_at" target="94335_r_at" />
    <edge source="93228_at" target="100772_g_at" />
    <edge source="93228_at" target="99809_at" />
    <edge source="93228_at" target="96224_at" />
    <edge source="93228_at" target="95735_at" />
    <edge source="93228_at" target="95283_at" />
    <edge source="93228_at" target="95738_at" />
    <edge source="93228_at" target="96047_at" />
    <edge source="93228_at" target="95327_at" />
    <edge source="93228_at" target="99070_at" />
    <edge source="93228_at" target="96768_at" />
    <edge source="93228_at" target="98036_at" />
    <edge source="93228_at" target="104135_at" />
    <edge source="93228_at" target="97786_at" />
    <edge source="93228_at" target="104610_at" />
    <edge source="93228_at" target="99843_at" />
    <edge source="93228_at" target="103614_at" />
    <edge source="93228_at" target="101334_at" />
    <edge source="93228_at" target="102003_at" />
    <edge source="93228_at" target="96130_at" />
    <edge source="93228_at" target="96866_at" />
    <edge source="97146_g_at" target="96334_f_at" />
    <edge source="97146_g_at" target="95738_at" />
    <edge source="97146_g_at" target="96047_at" />
    <edge source="97146_g_at" target="95758_at" />
    <edge source="97146_g_at" target="95283_at" />
    <edge source="97146_g_at" target="103469_at" />
    <edge source="97146_g_at" target="94380_at" />
    <edge source="97146_g_at" target="102084_f_at" />
    <edge source="97146_g_at" target="104560_at" />
    <edge source="96334_f_at" target="98036_at" />
    <edge source="96334_f_at" target="103643_at" />
    <edge source="96334_f_at" target="100554_at" />
    <edge source="96334_f_at" target="103469_at" />
    <edge source="96334_f_at" target="96829_at" />
    <edge source="96334_f_at" target="104120_at" />
    <edge source="96334_f_at" target="103706_at" />
    <edge source="96334_f_at" target="95043_at" />
    <edge source="96334_f_at" target="99809_at" />
    <edge source="96334_f_at" target="97819_at" />
    <edge source="96334_f_at" target="104135_at" />
    <edge source="96334_f_at" target="101667_at" />
    <edge source="96334_f_at" target="96276_r_at" />
    <edge source="96334_f_at" target="95738_at" />
    <edge source="96334_f_at" target="99070_at" />
    <edge source="96334_f_at" target="98295_at" />
    <edge source="96334_f_at" target="97786_at" />
    <edge source="96334_f_at" target="96866_at" />
    <edge source="96334_f_at" target="103699_i_at" />
    <edge source="96334_f_at" target="94380_at" />
    <edge source="96334_f_at" target="99179_at" />
    <edge source="96334_f_at" target="95758_at" />
    <edge source="96334_f_at" target="102084_f_at" />
    <edge source="96334_f_at" target="96598_at" />
    <edge source="96334_f_at" target="98320_at" />
    <edge source="99674_at" target="104610_at" />
    <edge source="99674_at" target="95738_at" />
    <edge source="99674_at" target="94380_at" />
    <edge source="96276_r_at" target="95283_at" />
    <edge source="96276_r_at" target="104120_at" />
    <edge source="96276_r_at" target="103699_i_at" />
    <edge source="96276_r_at" target="103469_at" />
    <edge source="96276_r_at" target="95758_at" />
    <edge source="96276_r_at" target="102084_f_at" />
    <edge source="96276_r_at" target="104560_at" />
    <edge source="104120_at" target="96829_at" />
    <edge source="104120_at" target="103706_at" />
    <edge source="104120_at" target="96224_at" />
    <edge source="104120_at" target="97742_s_at" />
    <edge source="104120_at" target="96047_at" />
    <edge source="104120_at" target="99070_at" />
    <edge source="104120_at" target="98036_at" />
    <edge source="104120_at" target="104610_at" />
    <edge source="104120_at" target="99843_at" />
    <edge source="104120_at" target="103699_i_at" />
    <edge source="104120_at" target="103614_at" />
    <edge source="104120_at" target="99179_at" />
    <edge source="104120_at" target="101334_at" />
    <edge source="104120_at" target="96598_at" />
    <edge source="104120_at" target="96866_at" />
    <edge source="100554_at" target="103643_at" />
    <edge source="100554_at" target="94380_at" />
    <edge source="100554_at" target="94335_r_at" />
    <edge source="100554_at" target="100772_g_at" />
    <edge source="100554_at" target="95043_at" />
    <edge source="100554_at" target="99809_at" />
    <edge source="100554_at" target="95735_at" />
    <edge source="100554_at" target="97819_at" />
    <edge source="100554_at" target="95327_at" />
    <edge source="100554_at" target="95738_at" />
    <edge source="100554_at" target="95283_at" />
    <edge source="100554_at" target="96224_at" />
    <edge source="100554_at" target="96047_at" />
    <edge source="100554_at" target="99070_at" />
    <edge source="100554_at" target="101334_at" />
    <edge source="100554_at" target="98036_at" />
    <edge source="100554_at" target="104135_at" />
    <edge source="100554_at" target="98295_at" />
    <edge source="100554_at" target="97786_at" />
    <edge source="100554_at" target="104610_at" />
    <edge source="100554_at" target="99843_at" />
    <edge source="100554_at" target="103614_at" />
    <edge source="100554_at" target="99179_at" />
    <edge source="100554_at" target="102084_f_at" />
    <edge source="100554_at" target="102003_at" />
    <edge source="100554_at" target="96130_at" />
    <edge source="100554_at" target="98320_at" />
    <edge source="96598_at" target="104610_at" />
    <edge source="96598_at" target="103699_i_at" />
    <edge source="96598_at" target="99070_at" />
    <edge source="96598_at" target="101334_at" />
    <edge source="96768_at" target="103699_i_at" />
    <edge source="96768_at" target="97742_s_at" />
    <edge source="96768_at" target="104560_at" />
    <edge source="96768_at" target="101334_at" />
    <edge source="98036_at" target="95758_at" />
    <edge source="98036_at" target="103469_at" />
    <edge source="98036_at" target="97819_at" />
    <edge source="98036_at" target="95283_at" />
    <edge source="98036_at" target="95738_at" />
    <edge source="98036_at" target="99070_at" />
    <edge source="98036_at" target="97786_at" />
    <edge source="98036_at" target="103699_i_at" />
    <edge source="98036_at" target="94380_at" />
    <edge source="98036_at" target="104560_at" />
    <edge source="98036_at" target="96130_at" />
    <edge source="104135_at" target="97742_s_at" />
    <edge source="104135_at" target="97819_at" />
    <edge source="104135_at" target="95283_at" />
    <edge source="104135_at" target="95738_at" />
    <edge source="104135_at" target="96047_at" />
    <edge source="104135_at" target="99070_at" />
    <edge source="104135_at" target="95735_at" />
    <edge source="104135_at" target="97786_at" />
    <edge source="104135_at" target="104610_at" />
    <edge source="104135_at" target="94380_at" />
    <edge source="104135_at" target="102084_f_at" />
    <edge source="104135_at" target="104560_at" />
    <edge source="104135_at" target="96130_at" />
    <edge source="97786_at" target="95283_at" />
    <edge source="97786_at" target="103614_at" />
    <edge source="97786_at" target="94335_r_at" />
    <edge source="97786_at" target="100772_g_at" />
    <edge source="97786_at" target="95043_at" />
    <edge source="97786_at" target="96130_at" />
    <edge source="97786_at" target="99809_at" />
    <edge source="97786_at" target="96224_at" />
    <edge source="97786_at" target="97819_at" />
    <edge source="97786_at" target="95738_at" />
    <edge source="97786_at" target="99179_at" />
    <edge source="97786_at" target="96047_at" />
    <edge source="97786_at" target="95327_at" />
    <edge source="97786_at" target="99070_at" />
    <edge source="97786_at" target="95735_at" />
    <edge source="97786_at" target="98295_at" />
    <edge source="97786_at" target="99843_at" />
    <edge source="97786_at" target="94380_at" />
    <edge source="97786_at" target="102084_f_at" />
    <edge source="97786_at" target="102003_at" />
    <edge source="97786_at" target="98320_at" />
    <edge source="104610_at" target="95283_at" />
    <edge source="104610_at" target="94380_at" />
    <edge source="104610_at" target="99809_at" />
    <edge source="104610_at" target="99070_at" />
    <edge source="104610_at" target="96224_at" />
    <edge source="104610_at" target="95738_at" />
    <edge source="104610_at" target="99843_at" />
    <edge source="104610_at" target="103614_at" />
    <edge source="104610_at" target="99179_at" />
    <edge source="104610_at" target="96130_at" />
    <edge source="104610_at" target="101334_at" />
    <edge source="99843_at" target="96047_at" />
    <edge source="99843_at" target="99070_at" />
    <edge source="99843_at" target="95735_at" />
    <edge source="99843_at" target="97742_s_at" />
    <edge source="99843_at" target="95283_at" />
    <edge source="99843_at" target="101334_at" />
    <edge source="103699_i_at" target="99179_at" />
    <edge source="103699_i_at" target="101667_at" />
    <edge source="103699_i_at" target="103706_at" />
    <edge source="103699_i_at" target="96866_at" />
    <edge source="103699_i_at" target="96829_at" />
    <edge source="103699_i_at" target="96224_at" />
    <edge source="103614_at" target="95283_at" />
    <edge source="103614_at" target="95738_at" />
    <edge source="103614_at" target="96047_at" />
    <edge source="103614_at" target="99070_at" />
    <edge source="103614_at" target="95735_at" />
    <edge source="103614_at" target="94380_at" />
    <edge source="103614_at" target="97819_at" />
    <edge source="103614_at" target="96130_at" />
    <edge source="103614_at" target="101334_at" />
    <edge source="103594_at" target="96224_at" />
    <edge source="99179_at" target="95738_at" />
    <edge source="99179_at" target="99070_at" />
    <edge source="99179_at" target="94380_at" />
    <edge source="99179_at" target="97819_at" />
    <edge source="99179_at" target="96130_at" />
    <edge source="99179_at" target="101334_at" />
    <edge source="95758_at" target="103643_at" />
    <edge source="95758_at" target="103469_at" />
    <edge source="95758_at" target="103706_at" />
    <edge source="95758_at" target="95043_at" />
    <edge source="95758_at" target="99809_at" />
    <edge source="95758_at" target="97819_at" />
    <edge source="95758_at" target="95738_at" />
    <edge source="95758_at" target="104560_at" />
    <edge source="95758_at" target="95283_at" />
    <edge source="95758_at" target="98295_at" />
    <edge source="95758_at" target="96829_at" />
    <edge source="95758_at" target="102084_f_at" />
    <edge source="95758_at" target="103439_at" />
    <edge source="95758_at" target="98320_at" />
    <edge source="102084_f_at" target="103643_at" />
    <edge source="102084_f_at" target="96829_at" />
    <edge source="102084_f_at" target="103469_at" />
    <edge source="102084_f_at" target="95043_at" />
    <edge source="102084_f_at" target="99809_at" />
    <edge source="102084_f_at" target="97819_at" />
    <edge source="102084_f_at" target="95738_at" />
    <edge source="102084_f_at" target="99070_at" />
    <edge source="102084_f_at" target="98295_at" />
    <edge source="102084_f_at" target="94380_at" />
    <edge source="102084_f_at" target="98320_at" />
    <edge source="104560_at" target="103643_at" />
    <edge source="104560_at" target="94380_at" />
    <edge source="104560_at" target="103469_at" />
    <edge source="104560_at" target="100772_g_at" />
    <edge source="104560_at" target="103706_at" />
    <edge source="104560_at" target="95738_at" />
    <edge source="104560_at" target="96047_at" />
    <edge source="104560_at" target="103439_at" />
    <edge source="104560_at" target="95283_at" />
    <edge source="104560_at" target="96829_at" />
    <edge source="104560_at" target="102003_at" />
    <edge source="103643_at" target="95283_at" />
    <edge source="103643_at" target="95738_at" />
    <edge source="103643_at" target="103469_at" />
    <edge source="103643_at" target="99070_at" />
    <edge source="103643_at" target="96130_at" />
    <edge source="103643_at" target="97742_s_at" />
    <edge source="103643_at" target="94380_at" />
    <edge source="103643_at" target="97819_at" />
    <edge source="97742_s_at" target="96047_at" />
    <edge source="97742_s_at" target="94335_r_at" />
    <edge source="97742_s_at" target="94380_at" />
    <edge source="97742_s_at" target="99809_at" />
    <edge source="97742_s_at" target="96130_at" />
    <edge source="97742_s_at" target="101334_at" />
    <edge source="103469_at" target="103706_at" />
    <edge source="103469_at" target="95043_at" />
    <edge source="103469_at" target="97819_at" />
    <edge source="103469_at" target="95283_at" />
    <edge source="103469_at" target="95738_at" />
    <edge source="103469_at" target="99070_at" />
    <edge source="103469_at" target="98295_at" />
    <edge source="103469_at" target="96829_at" />
    <edge source="103469_at" target="103439_at" />
    <edge source="103469_at" target="96130_at" />
    <edge source="103469_at" target="98320_at" />
    <edge source="96829_at" target="95283_at" />
    <edge source="94335_r_at" target="96047_at" />
    <edge source="94335_r_at" target="99070_at" />
    <edge source="94335_r_at" target="95735_at" />
    <edge source="94335_r_at" target="94380_at" />
    <edge source="94335_r_at" target="95283_at" />
    <edge source="94335_r_at" target="101334_at" />
    <edge source="103706_at" target="95283_at" />
    <edge source="103706_at" target="95738_at" />
    <edge source="103706_at" target="96047_at" />
    <edge source="103706_at" target="94380_at" />
    <edge source="101667_at" target="95738_at" />
    <edge source="101667_at" target="94380_at" />
    <edge source="95043_at" target="95738_at" />
    <edge source="95043_at" target="99070_at" />
    <edge source="95043_at" target="94380_at" />
    <edge source="95043_at" target="97819_at" />
    <edge source="100772_g_at" target="95283_at" />
    <edge source="100772_g_at" target="95738_at" />
    <edge source="100772_g_at" target="96047_at" />
    <edge source="100772_g_at" target="99070_at" />
    <edge source="100772_g_at" target="95735_at" />
    <edge source="100772_g_at" target="94380_at" />
    <edge source="100772_g_at" target="97819_at" />
    <edge source="100772_g_at" target="96130_at" />
    <edge source="99809_at" target="97819_at" />
    <edge source="99809_at" target="95738_at" />
    <edge source="99809_at" target="96047_at" />
    <edge source="99809_at" target="95283_at" />
    <edge source="99809_at" target="95735_at" />
    <edge source="99809_at" target="94380_at" />
    <edge source="99809_at" target="99070_at" />
    <edge source="99809_at" target="101334_at" />
    <edge source="97819_at" target="94380_at" />
    <edge source="97819_at" target="96130_at" />
    <edge source="97819_at" target="96224_at" />
    <edge source="97819_at" target="95738_at" />
    <edge source="97819_at" target="96047_at" />
    <edge source="97819_at" target="99070_at" />
    <edge source="97819_at" target="98295_at" />
    <edge source="97819_at" target="95327_at" />
    <edge source="97819_at" target="98320_at" />
    <edge source="95327_at" target="95283_at" />
    <edge source="95327_at" target="95738_at" />
    <edge source="95327_at" target="96047_at" />
    <edge source="95327_at" target="99070_at" />
    <edge source="95327_at" target="95735_at" />
    <edge source="95327_at" target="94380_at" />
    <edge source="95327_at" target="96130_at" />
    <edge source="95283_at" target="96130_at" />
    <edge source="95283_at" target="96224_at" />
    <edge source="95283_at" target="95738_at" />
    <edge source="95283_at" target="96047_at" />
    <edge source="95283_at" target="103439_at" />
    <edge source="95283_at" target="99070_at" />
    <edge source="95283_at" target="95735_at" />
    <edge source="95283_at" target="102003_at" />
    <edge source="95283_at" target="94380_at" />
    <edge source="96224_at" target="96130_at" />
    <edge source="96224_at" target="95738_at" />
    <edge source="96224_at" target="96047_at" />
    <edge source="96224_at" target="95735_at" />
    <edge source="96224_at" target="94380_at" />
    <edge source="96224_at" target="99070_at" />
    <edge source="96224_at" target="101334_at" />
    <edge source="95738_at" target="102003_at" />
    <edge source="95738_at" target="103439_at" />
    <edge source="95738_at" target="99070_at" />
    <edge source="95738_at" target="98295_at" />
    <edge source="95738_at" target="94380_at" />
    <edge source="95738_at" target="96130_at" />
    <edge source="95738_at" target="98320_at" />
    <edge source="96047_at" target="94380_at" />
    <edge source="96047_at" target="99070_at" />
    <edge source="96047_at" target="95735_at" />
    <edge source="96047_at" target="102003_at" />
    <edge source="96047_at" target="93901_at" />
    <edge source="102003_at" target="99070_at" />
    <edge source="102003_at" target="95735_at" />
    <edge source="102003_at" target="94380_at" />
    <edge source="99070_at" target="95735_at" />
    <edge source="99070_at" target="98295_at" />
    <edge source="99070_at" target="94380_at" />
    <edge source="99070_at" target="101334_at" />
    <edge source="99070_at" target="96130_at" />
    <edge source="99070_at" target="98320_at" />
    <edge source="98295_at" target="94380_at" />
    <edge source="94380_at" target="103439_at" />
    <edge source="94380_at" target="96130_at" />
    <edge source="94380_at" target="98320_at" />
  </graph>
</graphml>
